<?xml version='1.0' encoding='UTF-8'?>  
<!DOCTYPE hibernate-mapping PUBLIC  
 "-//Hibernate/Hibernate Mapping DTD 5.3//EN"  
 "http://hibernate.sourceforge.net/hibernate-mapping-3.0.dtd">  
 <hibernate-mapping>
 <class name="com.data.Product" table="sp_product">
 <id name="pid" column="ProductId">
 <generator class="assigned"/>
 </id>
 <property name="pname" column="ProductName"></property>
 <property name="cost" column="Cost">  </property>
  <property name="qty" column="Quantity">  </property>
 
 
  
 </class>
 
 
 </hibernate-mapping>